piceli/__init__.py
piceli/__main__.py
piceli/conf/__init__.py
piceli/conf/config_base.py
piceli/conf/config_k8s.py
piceli/conf/config_k8s_model.py
piceli/gcp/__init__.py
piceli/gcp/credentials.py
piceli/gcp/gke.py
piceli/k8s/__init__.py
piceli/k8s/cli/__init__.py
piceli/k8s/cli/common.py
piceli/k8s/cli/context.py
piceli/k8s/cli/deploy/__init__.py
piceli/k8s/cli/deploy/detail.py
piceli/k8s/cli/deploy/plan.py
piceli/k8s/cli/deploy/progress.py
piceli/k8s/cli/deploy/run.py
piceli/k8s/cli/model.py
piceli/k8s/config/__init__.py
piceli/k8s/config/kubeconfig.py
piceli/k8s/constants/__init__.py
piceli/k8s/constants/dry_run.py
piceli/k8s/constants/gke_compute_classes.py
piceli/k8s/constants/namespace.py
piceli/k8s/constants/phases.py
piceli/k8s/constants/policies.py
piceli/k8s/constants/secret_type.py
piceli/k8s/constants/strategies.py
piceli/k8s/constants/verbs.py
piceli/k8s/constants/wait_conditions.py
piceli/k8s/exceptions/api_exceptions.py
piceli/k8s/k8s_client/client.py
piceli/k8s/k8s_objects/base.py
piceli/k8s/object_manager/__init__.py
piceli/k8s/object_manager/base.py
piceli/k8s/object_manager/deployment.py
piceli/k8s/object_manager/factory.py
piceli/k8s/object_manager/service.py
piceli/k8s/object_manager/statefulset.py
piceli/k8s/object_manager/volumes.py
piceli/k8s/ops/__init__.py
piceli/k8s/ops/compare/__init__.py
piceli/k8s/ops/compare/compare_op.py
piceli/k8s/ops/compare/object_comparer.py
piceli/k8s/ops/compare/path.py
piceli/k8s/ops/deploy/__init__.py
piceli/k8s/ops/deploy/deploy_op.py
piceli/k8s/ops/deploy/deployment_executor.py
piceli/k8s/ops/deploy/deployment_graph.py
piceli/k8s/ops/deploy/deployment_order.py
piceli/k8s/ops/deploy/deployment_progress.py
piceli/k8s/ops/deploy/out_of_model_detector.py
piceli/k8s/ops/deploy/strategy_auto.py
piceli/k8s/ops/deploy/strategy_base.py
piceli/k8s/ops/fetcher.py
piceli/k8s/ops/loader.py
piceli/k8s/ops/sorter.py
piceli/k8s/ops/validators.py
piceli/k8s/templates/__init__.py
piceli/k8s/templates/auxiliary/__init__.py
piceli-0.0.5.dist-info/LICENSE
piceli-0.0.5.dist-info/METADATA
piceli-0.0.5.dist-info/WHEEL
piceli-0.0.5.dist-info/entry_points.txt
piceli-0.0.5.dist-info/RECORD
