Metadata-Version: 2.1
Name: piceli
Version: 0.0.5
Summary: Infrastructure for python
Home-page: https://www.pynenc.org
License: MIT
Author: Jose Diaz
Requires-Python: >=3.11.6,<4.0
Classifier: Development Status :: 2 - Pre-Alpha
Classifier: Environment :: Console
Classifier: Intended Audience :: Developers
Classifier: License :: OSI Approved :: MIT License
Classifier: Programming Language :: Python :: 3
Classifier: Programming Language :: Python :: 3.12
Classifier: Programming Language :: Python :: 3.11
Classifier: Topic :: Software Development :: Libraries :: Python Modules
Classifier: Topic :: System :: Distributed Computing
Requires-Dist: cistell (>=0.0.4,<0.0.5)
Requires-Dist: cron-validator (>=1.0.8,<2.0.0)
Requires-Dist: kubernetes (>=29.0.0,<30.0.0)
Requires-Dist: pydantic (>=2.6.1,<3.0.0)
Requires-Dist: tenacity (>=8.2.3,<9.0.0)
Requires-Dist: textual (>=0.49.0,<0.50.0)
Requires-Dist: typer[all] (>=0.9.0,<0.10.0)
Project-URL: Documentation, https://docs.piceli.pynenc.org
Project-URL: Repository, https://github.com/pynenc/piceli
